Metadata-Version: 2.1
Name: trekpy
Version: 0.0.1
Summary: Using graph theory algorithms and simulations, to optimaize paths and travel times between nodes on a geospatial map
Home-page: https://github.com/teddyoweh/Trek
Author: Teddy Oweh
Author-email: teddyoweh@gmail.com
License: MIT
Keywords: Trek
Classifier: Development Status :: 3 - Alpha
Classifier: Intended Audience :: Developers
Classifier: License :: OSI Approved :: MIT License
Classifier: Programming Language :: Python :: 3
